examples/__init__.py
examples/auth_step_01.py
examples/auth_step_02.py
examples/create_feed_item.py
examples/get_accounts.py
examples/get_whoami.py
monzo/__init__.py
monzo/authentication.py
monzo/exceptions.py
monzo/helpers.py
monzo/httpio.py
monzo/endpoints/__init__.py
monzo/endpoints/account.py
monzo/endpoints/attachment.py
monzo/endpoints/balance.py
monzo/endpoints/feed_item.py
monzo/endpoints/monzo.py
monzo/endpoints/pot.py
monzo/endpoints/receipt.py
monzo/endpoints/transaction.py
monzo/endpoints/webhooks.py
monzo/endpoints/whoami.py
monzo/handlers/__init__.py
monzo/handlers/filesystem.py
monzo/handlers/storage.py
tests/__init__.py
tests/helpers.py
tests/test_authentication.py
tests/test_endpoints.py
tests/test_payload.py
tests/mock_payloads/__init__.py
tests/mock_responses/__init__.py
Monzo_API-1.2.0.dist-info/LICENSE
Monzo_API-1.2.0.dist-info/METADATA
Monzo_API-1.2.0.dist-info/WHEEL
Monzo_API-1.2.0.dist-info/top_level.txt
Monzo_API-1.2.0.dist-info/RECORD
