Metadata-Version: 2.1
Name: Monzo-API
Version: 1.2.0
Summary: Package to interact with the API provided by Monzo bank
Home-page: https://github.com/petermcd/monzo-api
Author: Peter McDonald
Author-email: git@petermcdonald.co.uk
Project-URL: Bug Tracker, https://github.com/petermcd/monzo-api/issues
Project-URL: Documentation, https://monzo-api.readthedocs.io
Project-URL: Source, https://github.com/petermcd/monzo-api
Classifier: Programming Language :: Python :: 3.8
Classifier: Programming Language :: Python :: 3.9
Classifier: Programming Language :: Python :: 3.10
Classifier: Programming Language :: Python :: 3.11
Classifier: Programming Language :: Python :: 3.12
Classifier: License :: OSI Approved :: MIT License
Classifier: Operating System :: OS Independent
Classifier: Intended Audience :: Developers
Classifier: Topic :: Office/Business :: Financial
Requires-Python: >=3.8
License-File: LICENSE
Provides-Extra: build
Requires-Dist: wheel; extra == "build"
Requires-Dist: build; extra == "build"
Provides-Extra: docs
Requires-Dist: sphinx; extra == "docs"
Requires-Dist: sphinx-rtd-theme; extra == "docs"
Provides-Extra: test
Requires-Dist: flake8; extra == "test"
Requires-Dist: isort; extra == "test"
Requires-Dist: mypy; extra == "test"
Requires-Dist: pytest; extra == "test"
Requires-Dist: pytest-mock; extra == "test"
